quartustcl/__init__.py
quartustcl/__main__.py
quartustcl-0.3.dist-info/LICENSE
quartustcl-0.3.dist-info/METADATA
quartustcl-0.3.dist-info/WHEEL
quartustcl-0.3.dist-info/top_level.txt
quartustcl-0.3.dist-info/RECORD
