Metadata-Version: 2.1
Name: quartustcl
Version: 0.3
Summary: a Python package for interfacing with Intel Quartus Tcl
Home-page: https://github.com/agrif/quartustcl/
Author: Aaron Griffith
Author-email: aargri@gmail.com
License: MIT
Project-URL: Source, https://github.com/agrif/quartustcl/
Project-URL: Documentation, https://quartustcl.readthedocs.io/en/latest/
Keywords: quartus tcl
Platform: any
Classifier: Development Status :: 4 - Beta
Classifier: Intended Audience :: Developers
Classifier: Topic :: Software Development :: Libraries :: Python Modules
Classifier: Topic :: Scientific/Engineering :: Electronic Design Automation (EDA)
Classifier: License :: OSI Approved :: MIT License
Classifier: Programming Language :: Python :: 3
Requires-Python: >=3.5
Provides-Extra: docs
Requires-Dist: mkdocs (<1.1,>=1.0) ; extra == 'docs'
Requires-Dist: mkautodoc (>=0.1.0) ; extra == 'docs'
